Metadata-Version: 2.1
Name: swaggerspect
Version: 0.1.5
Home-page: https://github.com/emerald-geomodelling/swaggerspect
Author: Egil Moeller
Author-email: em@emrld.no
License-File: LICENSE
Requires-Dist: numpydoc
Requires-Dist: jsonschema
